{"cameraMode":{"drawMode":0,"name":"Shaded","section":"Shading Mode"},"sceneLighting":false,"audioPlay":false,"sceneViewState":{"m_AlwaysRefresh":false,"showFog":true,"showSkybox":false,"showFlares":true,"showImageEffects":true,"showParticleSystems":true,"showVisualEffectGraphs":true,"m_FxEnabled":true},"in2DMode":false,"pivot":{"x":16.15373420715332,"y":20.192434310913087,"z":-4.909636974334717},"rotation":{"x":0.015610283240675927,"y":-0.9822062253952026,"z":0.1575072705745697,"w":0.09733320772647858},"size":0.9937706589698792,"orthographic":false}